yczz_st/__init__.py
yczz_st/yczz_double.py
yczz_st/yczz_single.py
yczz_st-0.0.3.dist-info/METADATA
yczz_st-0.0.3.dist-info/WHEEL
yczz_st-0.0.3.dist-info/top_level.txt
yczz_st-0.0.3.dist-info/RECORD
