Metadata-Version: 2.1
Name: yczz-st
Version: 0.0.3
Summary: yczz_st 时空协同杨赤中滤波插值法
Home-page: https://github.com/Spiderguy-07/yczz_st
Author: wyd_hzq_sww_yql
Author-email: 2396188089@qq.com
License: UNKNOWN
Platform: UNKNOWN
